asoke/__init__.py
asoke/app.py
asoke/dispatcher.py
asoke/errors.py
asoke-0.0.2.dist-info/LICENSE
asoke-0.0.2.dist-info/METADATA
asoke-0.0.2.dist-info/WHEEL
asoke-0.0.2.dist-info/top_level.txt
asoke-0.0.2.dist-info/RECORD
