Metadata-Version: 2.1
Name: asoke
Version: 0.0.2
Summary: A simple class-based dispatcher for ASGI apps and a quickstart wrapper
Home-page: https://declassed.art/repository/asoke
Author: AXY
Author-email: axy@declassed.art
License: UNKNOWN
Platform: UNKNOWN
Classifier: Programming Language :: Python :: 3
Classifier: License :: OSI Approved :: BSD License
Classifier: Operating System :: OS Independent
Classifier: Intended Audience :: Developers
Classifier: Development Status :: 3 - Alpha
Classifier: Topic :: Internet :: WWW/HTTP
Requires-Python: >=3.6
License-File: LICENSE
Requires-Dist: hypercorn
Requires-Dist: starlette
Requires-Dist: uvloop
